gopro_renamer/__init__.py
gopro_renamer/renamer.py
gopro_renamer-0.5.0.dist-info/LICENSE
gopro_renamer-0.5.0.dist-info/METADATA
gopro_renamer-0.5.0.dist-info/WHEEL
gopro_renamer-0.5.0.dist-info/entry_points.txt
gopro_renamer-0.5.0.dist-info/top_level.txt
gopro_renamer-0.5.0.dist-info/RECORD
