Metadata-Version: 2.1
Name: gopro-renamer
Version: 0.5.0
Summary: Rename chaptered video files created by GoPro cameras
Home-page: https://github.com/kcha/gopro_renamer
Author: Kevin Ha
License: UNKNOWN
Project-URL: Bug Tracker, https://github.com/kcha/gopro_renamer/issues
Platform: UNKNOWN
Classifier: Programming Language :: Python :: 3
Classifier: License :: OSI Approved :: MIT License
Classifier: Operating System :: OS Independent
Classifier: Topic :: Utilities
Requires-Python: >=3.6
License-File: LICENSE
